{
	"configurations" : 
	[
		{
			"directories" : 
			[
				{
					"build" : ".",
					"childIndexes" : 
					[
						1,
						2,
						3
					],
					"jsonFile" : "directory-.-Debug-f5ebdc15457944623624.json",
					"minimumCMakeVersion" : 
					{
						"string" : "3.9"
					},
					"projectIndex" : 0,
					"source" : "."
				},
				{
					"build" : "exo1",
					"jsonFile" : "directory-exo1-Debug-2c8c37ba8083273e78ef.json",
					"minimumCMakeVersion" : 
					{
						"string" : "3.9"
					},
					"parentIndex" : 0,
					"projectIndex" : 0,
					"source" : "exo1",
					"targetIndexes" : 
					[
						0
					]
				},
				{
					"build" : "exo2",
					"jsonFile" : "directory-exo2-Debug-52596b095dfd213ee8ba.json",
					"minimumCMakeVersion" : 
					{
						"string" : "3.9"
					},
					"parentIndex" : 0,
					"projectIndex" : 0,
					"source" : "exo2",
					"targetIndexes" : 
					[
						1
					]
				},
				{
					"build" : "exo3",
					"jsonFile" : "directory-exo3-Debug-c89bc7bd33193bce9eb4.json",
					"minimumCMakeVersion" : 
					{
						"string" : "3.9"
					},
					"parentIndex" : 0,
					"projectIndex" : 0,
					"source" : "exo3",
					"targetIndexes" : 
					[
						2
					]
				}
			],
			"name" : "Debug",
			"projects" : 
			[
				{
					"directoryIndexes" : 
					[
						0,
						1,
						2,
						3
					],
					"name" : "TP4",
					"targetIndexes" : 
					[
						0,
						1,
						2
					]
				}
			],
			"targets" : 
			[
				{
					"directoryIndex" : 1,
					"id" : "exo1::@acf1987dcf78f933f694",
					"jsonFile" : "target-exo1-Debug-b1948c3d0ff85bd80a7e.json",
					"name" : "exo1",
					"projectIndex" : 0
				},
				{
					"directoryIndex" : 2,
					"id" : "exo2::@8e0ef2c91cec2f4253a6",
					"jsonFile" : "target-exo2-Debug-9da3c1fb14d7493938d0.json",
					"name" : "exo2",
					"projectIndex" : 0
				},
				{
					"directoryIndex" : 3,
					"id" : "exo3::@320c748ffa17a640c38a",
					"jsonFile" : "target-exo3-Debug-ae1e184fc124e7f3843a.json",
					"name" : "exo3",
					"projectIndex" : 0
				}
			]
		}
	],
	"kind" : "codemodel",
	"paths" : 
	{
		"build" : "/home/julesr0y/Repos/TP_PROG_CIR2/TP4/cmake-build-debug",
		"source" : "/home/julesr0y/Repos/TP_PROG_CIR2/TP4"
	},
	"version" : 
	{
		"major" : 2,
		"minor" : 5
	}
}
